setup.py
facebook_login/__init__.py
facebook_login/login.py
facebook_login.egg-info/PKG-INFO
facebook_login.egg-info/SOURCES.txt
facebook_login.egg-info/dependency_links.txt
facebook_login.egg-info/requires.txt
facebook_login.egg-info/top_level.txt