Metadata-Version: 2.1
Name: facebook-login
Version: 0.1
Requires-Dist: selenium
